MukuroL/__init__.py
MukuroL/mkl.py
MukuroL/test.py
MukuroL/core/__init__.py
MukuroL/core/basic_tmpls.py
MukuroL/core/converter.py
MukuroL/core/mukurol.py
MukuroL/core/parser.py
MukuroL/core/renderer.py
MukuroL/core/test.py
MukuroL/core/tokenizer.py
MukuroL-0.1.6.dist-info/LICENSE
MukuroL-0.1.6.dist-info/METADATA
MukuroL-0.1.6.dist-info/WHEEL
MukuroL-0.1.6.dist-info/entry_points.txt
MukuroL-0.1.6.dist-info/top_level.txt
MukuroL-0.1.6.dist-info/RECORD
