Metadata-Version: 2.1
Name: MukuroL
Version: 0.1.6
Summary: MukuroL is a lightweight markup language, designed exclusively for wireframe creation using simple code.
Home-page: 
Author: collabologic
Author-email: 
Classifier: Programming Language :: Python :: 3
Classifier: License :: OSI Approved :: MIT License
Classifier: Operating System :: OS Independent
Requires-Python: >=3.6
License-File: LICENSE
Requires-Dist: beautifulsoup4
Requires-Dist: watchdog
Requires-Dist: PyYAML
Requires-Dist: Jinja2
